[
    {
        "itstId": "109",
        "itstNm": "서초삼성스위트아파트",
        "mapCtptIntLat": 37.4953066,
        "mapCtptIntLot": 127.0250233,
        "NewmapCtptIntLat": 37.4952168,
        "NewmapCtptIntLot": 127.0250233,
        "MaxStopetPdsgRmdrCs": 660,
        "protectedMaxAllowedetPdsgRmdrCs": 220,
        "MaxStopstPdsgRmdrCs": 650,
        "protectedMaxAllowedstPdsgRmdrCs": 240
    },
    {
        "itstId": "111",
        "itstNm": "현대빌딩본관",
        "mapCtptIntLat": 37.5773531,
        "mapCtptIntLot": 126.9881574,
        "NewmapCtptIntLat": 37.5774429,
        "NewmapCtptIntLot": 126.9881574,
        "protectedMaxAllowedntPdsgRmdrCs": 310
    },
    {
        "itstId": "148",
        "itstNm": "국회의사당",
        "mapCtptIntLat": 37.5288059,
        "mapCtptIntLot": 126.9165964,
        "NewmapCtptIntLat": 37.5288957,
        "NewmapCtptIntLot": 126.9164831,
        "MaxStopnePdsgRmdrCs": 520,
        "protectedMaxAllowednePdsgRmdrCs": 370,
        "MaxStopnwPdsgRmdrCs": 1190,
        "protectedMaxAllowednwPdsgRmdrCs": 410
    },
    {
        "itstId": "149",
        "itstNm": "국회도서관",
        "mapCtptIntLat": 37.5303325,
        "mapCtptIntLot": 126.9190971,
        "NewmapCtptIntLat": 37.5304223,
        "NewmapCtptIntLot": 126.9189838,
        "MaxStopnwPdsgRmdrCs": 2550,
        "protectedMaxAllowednwPdsgRmdrCs": 2550
    },
    {
        "itstId": "150",
        "itstNm": "서울디자인지원센터",
        "mapCtptIntLat": 37.5729392,
        "mapCtptIntLot": 127.0075758,
        "NewmapCtptIntLat": 37.5728494,
        "NewmapCtptIntLot": 127.0074625,
        "MaxStopswPdsgRmdrCs": 1100,
        "protectedMaxAllowedswPdsgRmdrCs": 300
    },
    {
        "itstId": "151",
        "itstNm": "이화사거리",
        "mapCtptIntLat": 37.5761684,
        "mapCtptIntLot": 127.0022106,
        "NewmapCtptIntLat": 37.5761684,
        "NewmapCtptIntLot": 127.0020973,
        "MaxStopntPdsgRmdrCs": 1260,
        "protectedMaxAllowedntPdsgRmdrCs": 290,
        "MaxStopetPdsgRmdrCs": 1030,
        "protectedMaxAllowedetPdsgRmdrCs": 370,
        "MaxStopstPdsgRmdrCs": 1150,
        "protectedMaxAllowedstPdsgRmdrCs": 240,
        "MaxStopwtPdsgRmdrCs": 1030,
        "protectedMaxAllowedwtPdsgRmdrCs": 370
    },
    {
        "itstId": "156",
        "itstNm": "혜화동로터리",
        "mapCtptIntLat": 37.5855368,
        "mapCtptIntLot": 127.0011974,
        "NewmapCtptIntLat": 37.585447,
        "NewmapCtptIntLot": 127.001084,
        "MaxStopstPdsgRmdrCs": 1030,
        "protectedMaxAllowedstPdsgRmdrCs": 380,
        "MaxStopswPdsgRmdrCs": 1010,
        "protectedMaxAllowedswPdsgRmdrCs": 390
    },
    {
        "itstId": "157",
        "itstNm": "세운상가",
        "mapCtptIntLat": 37.5705684,
        "mapCtptIntLot": 126.9950438,
        "NewmapCtptIntLat": 37.5706582,
        "NewmapCtptIntLot": 126.9950438,
        "MaxStopntPdsgRmdrCs": 990,
        "protectedMaxAllowedntPdsgRmdrCs": 390
    },
    {
        "itstId": "158",
        "itstNm": "청계6가",
        "mapCtptIntLat": 37.5699421,
        "mapCtptIntLot": 127.0096899,
        "NewmapCtptIntLat": 37.5698523,
        "NewmapCtptIntLot": 127.0096899,
        "MaxStopntPdsgRmdrCs": 1200,
        "protectedMaxAllowedntPdsgRmdrCs": 500,
        "MaxStopstPdsgRmdrCs": 620,
        "protectedMaxAllowedstPdsgRmdrCs": 500
    },
    {
        "itstId": "160",
        "itstNm": "삼성힐스테이트2단지앞",
        "mapCtptIntLat": 37.512433,
        "mapCtptIntLot": 127.0511972,
        "NewmapCtptIntLat": 37.5123432,
        "NewmapCtptIntLot": 127.0511972,
        "MaxStopstPdsgRmdrCs": 1200,
        "protectedMaxAllowedstPdsgRmdrCs": 380
    },
    {
        "itstId": "173",
        "itstNm": "영동전화국",
        "mapCtptIntLat": 37.5050323,
        "mapCtptIntLot": 127.0416266,
        "NewmapCtptIntLat": 37.5050323,
        "NewmapCtptIntLot": 127.0415134,
        "MaxStopwtPdsgRmdrCs": 1240,
        "protectedMaxAllowedwtPdsgRmdrCs": 360
    },
    {
        "itstId": "175",
        "itstNm": "역삼금호어울림",
        "mapCtptIntLat": 37.4926506,
        "mapCtptIntLot": 127.0340999,
        "NewmapCtptIntLat": 37.4926506,
        "NewmapCtptIntLot": 127.0342131,
        "MaxStopetPdsgRmdrCs": 580,
        "protectedMaxAllowedetPdsgRmdrCs": 270
    },
    {
        "itstId": "176",
        "itstNm": "우리은행역삼",
        "mapCtptIntLat": 37.4935164,
        "mapCtptIntLot": 127.0403703,
        "NewmapCtptIntLat": 37.4935164,
        "NewmapCtptIntLot": 127.0404835,
        "MaxStopetPdsgRmdrCs": 1280,
        "protectedMaxAllowedetPdsgRmdrCs": 310
    },
    {
        "itstId": "198",
        "itstNm": "신도림역",
        "mapCtptIntLat": 37.5102262,
        "mapCtptIntLot": 126.8903682,
        "NewmapCtptIntLat": 37.510316,
        "NewmapCtptIntLot": 126.890255,
        "MaxStopnePdsgRmdrCs": 900,
        "protectedMaxAllowednePdsgRmdrCs": 300,
        "MaxStopnwPdsgRmdrCs": 1270,
        "protectedMaxAllowednwPdsgRmdrCs": 430
    },
    {
        "itstId": "199",
        "itstNm": "신도림주민센터",
        "mapCtptIntLat": 37.5057642,
        "mapCtptIntLot": 126.8836059,
        "NewmapCtptIntLat": 37.505854,
        "NewmapCtptIntLot": 126.8834927,
        "MaxStopnePdsgRmdrCs": 760,
        "protectedMaxAllowednePdsgRmdrCs": 230,
        "MaxStopsePdsgRmdrCs": 1380,
        "protectedMaxAllowedsePdsgRmdrCs": 320,
        "MaxStopnwPdsgRmdrCs": 1360,
        "protectedMaxAllowednwPdsgRmdrCs": 340
    },
    {
        "itstId": "200",
        "itstNm": "구로역",
        "mapCtptIntLat": 37.5030259,
        "mapCtptIntLot": 126.8798092,
        "NewmapCtptIntLat": 37.5031157,
        "NewmapCtptIntLot": 126.879696,
        "MaxStopnePdsgRmdrCs": 1500,
        "protectedMaxAllowednePdsgRmdrCs": 290,
        "MaxStopsePdsgRmdrCs": 1400,
        "protectedMaxAllowedsePdsgRmdrCs": 390,
        "MaxStopswPdsgRmdrCs": 1500,
        "protectedMaxAllowedswPdsgRmdrCs": 300,
        "MaxStopnwPdsgRmdrCs": 1400,
        "protectedMaxAllowednwPdsgRmdrCs": 390
    },
    {
        "itstId": "201",
        "itstNm": "중앙유통단지",
        "mapCtptIntLat": 37.5011484,
        "mapCtptIntLot": 126.8772342,
        "NewmapCtptIntLat": 37.5010586,
        "NewmapCtptIntLot": 126.8773474,
        "MaxStopnePdsgRmdrCs": 700,
        "protectedMaxAllowednePdsgRmdrCs": 310,
        "MaxStopsePdsgRmdrCs": 1320,
        "protectedMaxAllowedsePdsgRmdrCs": 370
    },
    {
        "itstId": "202",
        "itstNm": "고척교",
        "mapCtptIntLat": 37.4988847,
        "mapCtptIntLot": 126.8717925,
        "NewmapCtptIntLat": 37.4988847,
        "NewmapCtptIntLot": 126.8716793,
        "MaxStopetPdsgRmdrCs": 1100,
        "protectedMaxAllowedetPdsgRmdrCs": 600,
        "MaxStopwtPdsgRmdrCs": 1100,
        "protectedMaxAllowedwtPdsgRmdrCs": 600
    },
    {
        "itstId": "209",
        "itstNm": "수색교",
        "mapCtptIntLat": 37.5870096,
        "mapCtptIntLot": 126.8872464,
        "NewmapCtptIntLat": 37.5870994,
        "NewmapCtptIntLot": 126.887133,
        "MaxStopnePdsgRmdrCs": 1040,
        "protectedMaxAllowednePdsgRmdrCs": 370,
        "MaxStopnwPdsgRmdrCs": 1070,
        "protectedMaxAllowednwPdsgRmdrCs": 340
    },
    {
        "itstId": "210",
        "itstNm": "수색서광빌딩",
        "mapCtptIntLat": 37.5839318,
        "mapCtptIntLot": 126.8918782,
        "NewmapCtptIntLat": 37.583842,
        "NewmapCtptIntLot": 126.8917648,
        "MaxStopswPdsgRmdrCs": 1050,
        "protectedMaxAllowedswPdsgRmdrCs": 340
    },
    {
        "itstId": "211",
        "itstNm": "LG베스트샵수색점",
        "mapCtptIntLat": 37.583171,
        "mapCtptIntLot": 126.8936698,
        "NewmapCtptIntLat": 37.5830812,
        "NewmapCtptIntLot": 126.8935564,
        "MaxStopswPdsgRmdrCs": 960,
        "protectedMaxAllowedswPdsgRmdrCs": 430
    },
    {
        "itstId": "212",
        "itstNm": "수색역",
        "mapCtptIntLat": 37.5821709,
        "mapCtptIntLot": 126.8954205,
        "NewmapCtptIntLat": 37.5820811,
        "NewmapCtptIntLot": 126.8953071,
        "MaxStopnePdsgRmdrCs": 1090,
        "protectedMaxAllowednePdsgRmdrCs": 300,
        "MaxStopsePdsgRmdrCs": 970,
        "protectedMaxAllowedsePdsgRmdrCs": 410,
        "MaxStopswPdsgRmdrCs": 1090,
        "protectedMaxAllowedswPdsgRmdrCs": 300
    },
    {
        "itstId": "213",
        "itstNm": "수색디지털프라자",
        "mapCtptIntLat": 37.5808112,
        "mapCtptIntLot": 126.8976958,
        "NewmapCtptIntLat": 37.580901,
        "NewmapCtptIntLot": 126.8978092,
        "MaxStopnePdsgRmdrCs": 1060,
        "protectedMaxAllowednePdsgRmdrCs": 340
    },
    {
        "itstId": "214",
        "itstNm": "수색E마트앞",
        "mapCtptIntLat": 37.5795337,
        "mapCtptIntLot": 126.8998951,
        "NewmapCtptIntLat": 37.5796235,
        "NewmapCtptIntLot": 126.8997817,
        "MaxStopnePdsgRmdrCs": 1050,
        "protectedMaxAllowednePdsgRmdrCs": 330,
        "MaxStopsePdsgRmdrCs": 1070,
        "protectedMaxAllowedsePdsgRmdrCs": 330,
        "MaxStopswPdsgRmdrCs": 1050,
        "protectedMaxAllowedswPdsgRmdrCs": 330,
        "MaxStopnwPdsgRmdrCs": 1070,
        "protectedMaxAllowednwPdsgRmdrCs": 330
    },
    {
        "itstId": "1069",
        "itstNm": "동일로지하차도",
        "mapCtptIntLat": 37.5950098,
        "mapCtptIntLot": 127.0803091,
        "NewmapCtptIntLat": 37.5950098,
        "NewmapCtptIntLot": 127.0801957,
        "MaxStopntPdsgRmdrCs": 1260,
        "protectedMaxAllowedntPdsgRmdrCs": 340,
        "MaxStopetPdsgRmdrCs": 1120,
        "protectedMaxAllowedetPdsgRmdrCs": 480,
        "MaxStopstPdsgRmdrCs": 1260,
        "protectedMaxAllowedstPdsgRmdrCs": 340,
        "MaxStopwtPdsgRmdrCs": 1120,
        "protectedMaxAllowedwtPdsgRmdrCs": 480
    },
    {
        "itstId": "1109",
        "itstNm": "서울혁신파크",
        "mapCtptIntLat": 37.608822,
        "mapCtptIntLot": 126.9313876,
        "NewmapCtptIntLat": 37.6089118,
        "NewmapCtptIntLot": 126.9312742,
        "MaxStopnePdsgRmdrCs": 1250,
        "protectedMaxAllowednePdsgRmdrCs": 330,
        "MaxStopsePdsgRmdrCs": 720,
        "protectedMaxAllowedsePdsgRmdrCs": 320,
        "MaxStopswPdsgRmdrCs": 1250,
        "protectedMaxAllowedswPdsgRmdrCs": 330,
        "MaxStopnwPdsgRmdrCs": 1260,
        "protectedMaxAllowednwPdsgRmdrCs": 320
    },
    {
        "itstId": "1123",
        "itstNm": "대치삼성아파트앞",
        "mapCtptIntLat": 37.4982423,
        "mapCtptIntLot": 127.0588972,
        "NewmapCtptIntLat": 37.4982423,
        "NewmapCtptIntLot": 127.058784,
        "MaxStopntPdsgRmdrCs": 1300,
        "protectedMaxAllowedntPdsgRmdrCs": 350,
        "MaxStopetPdsgRmdrCs": 680,
        "protectedMaxAllowedetPdsgRmdrCs": 340,
        "MaxStopstPdsgRmdrCs": 1300,
        "protectedMaxAllowedstPdsgRmdrCs": 350,
        "MaxStopwtPdsgRmdrCs": 680,
        "protectedMaxAllowedwtPdsgRmdrCs": 340
    },
    {
        "itstId": "1168",
        "itstNm": "길음역",
        "mapCtptIntLat": 37.6042801,
        "mapCtptIntLot": 127.0251618,
        "NewmapCtptIntLat": 37.6041903,
        "NewmapCtptIntLot": 127.0250484,
        "MaxStopnePdsgRmdrCs": 740,
        "protectedMaxAllowednePdsgRmdrCs": 250,
        "MaxStopswPdsgRmdrCs": 1230,
        "protectedMaxAllowedswPdsgRmdrCs": 370
    },
    {
        "itstId": "1183",
        "itstNm": "서초푸르지오써밋",
        "mapCtptIntLat": 37.5017678,
        "mapCtptIntLot": 127.0219365,
        "NewmapCtptIntLat": 37.5017678,
        "NewmapCtptIntLot": 127.0220497,
        "MaxStopetPdsgRmdrCs": 490,
        "protectedMaxAllowedetPdsgRmdrCs": 310
    },
    {
        "itstId": "1207",
        "itstNm": "서이지구대",
        "mapCtptIntLat": 37.4925273,
        "mapCtptIntLot": 127.0282361,
        "NewmapCtptIntLat": 37.4926171,
        "NewmapCtptIntLot": 127.0282361,
        "MaxStopntPdsgRmdrCs": 2550,
        "protectedMaxAllowedntPdsgRmdrCs": 2550
    },
    {
        "itstId": "1219",
        "itstNm": "홍대역2번출구",
        "mapCtptIntLat": 37.5567035,
        "mapCtptIntLot": 126.9236053,
        "NewmapCtptIntLat": 37.5567933,
        "NewmapCtptIntLot": 126.923492,
        "MaxStopnwPdsgRmdrCs": 1200,
        "protectedMaxAllowednwPdsgRmdrCs": 490
    },
    {
        "itstId": "1224",
        "itstNm": "망우역",
        "mapCtptIntLat": 37.5981879,
        "mapCtptIntLot": 127.0928062,
        "NewmapCtptIntLat": 37.5981879,
        "NewmapCtptIntLot": 127.0926928,
        "MaxStopntPdsgRmdrCs": 1130,
        "protectedMaxAllowedntPdsgRmdrCs": 460,
        "MaxStopetPdsgRmdrCs": 1140,
        "protectedMaxAllowedetPdsgRmdrCs": 460,
        "MaxStopstPdsgRmdrCs": 1130,
        "protectedMaxAllowedstPdsgRmdrCs": 460,
        "MaxStopwtPdsgRmdrCs": 1200,
        "protectedMaxAllowedwtPdsgRmdrCs": 400
    },
    {
        "itstId": "1225",
        "itstNm": "코스트코상봉",
        "mapCtptIntLat": 37.5977124,
        "mapCtptIntLot": 127.0907475,
        "NewmapCtptIntLat": 37.5978022,
        "NewmapCtptIntLot": 127.0907475,
        "MaxStopntPdsgRmdrCs": 1120,
        "protectedMaxAllowedntPdsgRmdrCs": 470
    },
    {
        "itstId": "1226",
        "itstNm": "상봉지하차도",
        "mapCtptIntLat": 37.5970829,
        "mapCtptIntLot": 127.0880897,
        "NewmapCtptIntLat": 37.5969931,
        "NewmapCtptIntLot": 127.0880897,
        "MaxStopntPdsgRmdrCs": 1270,
        "protectedMaxAllowedntPdsgRmdrCs": 310,
        "MaxStopetPdsgRmdrCs": 1240,
        "protectedMaxAllowedetPdsgRmdrCs": 360,
        "MaxStopstPdsgRmdrCs": 1240,
        "protectedMaxAllowedstPdsgRmdrCs": 360
    },
    {
        "itstId": "1228",
        "itstNm": "상봉역",
        "mapCtptIntLat": 37.5963673,
        "mapCtptIntLot": 127.0855416,
        "NewmapCtptIntLat": 37.5963673,
        "NewmapCtptIntLot": 127.0854282,
        "MaxStopntPdsgRmdrCs": 1270,
        "protectedMaxAllowedntPdsgRmdrCs": 310,
        "MaxStopwtPdsgRmdrCs": 1320,
        "protectedMaxAllowedwtPdsgRmdrCs": 270
    },
    {
        "itstId": "1229",
        "itstNm": "서울중랑우체국",
        "mapCtptIntLat": 37.5958166,
        "mapCtptIntLot": 127.0834891,
        "NewmapCtptIntLat": 37.5957268,
        "NewmapCtptIntLot": 127.0834891,
        "MaxStopstPdsgRmdrCs": 1180,
        "protectedMaxAllowedstPdsgRmdrCs": 410
    },
    {
        "itstId": "1230",
        "itstNm": "우리은행중랑교지점",
        "mapCtptIntLat": 37.5936973,
        "mapCtptIntLot": 127.0750493,
        "NewmapCtptIntLat": 37.5936075,
        "NewmapCtptIntLot": 127.0750493,
        "MaxStopstPdsgRmdrCs": 1190,
        "protectedMaxAllowedstPdsgRmdrCs": 390
    },
    {
        "itstId": "1283",
        "itstNm": "제일제당앞",
        "mapCtptIntLat": 37.499753,
        "mapCtptIntLot": 126.8746312,
        "NewmapCtptIntLat": 37.4996632,
        "NewmapCtptIntLot": 126.8747444,
        "MaxStopsePdsgRmdrCs": 1200,
        "protectedMaxAllowedsePdsgRmdrCs": 500
    },
    {
        "itstId": "1284",
        "itstNm": "신도림대우푸르지오",
        "mapCtptIntLat": 37.5094222,
        "mapCtptIntLot": 126.8888701,
        "NewmapCtptIntLat": 37.5093324,
        "NewmapCtptIntLot": 126.8889833,
        "MaxStopsePdsgRmdrCs": 1120,
        "protectedMaxAllowedsePdsgRmdrCs": 570
    },
    {
        "itstId": "1294",
        "itstNm": "여의도공원",
        "mapCtptIntLat": 37.5242539,
        "mapCtptIntLot": 126.9216726,
        "NewmapCtptIntLat": 37.5241641,
        "NewmapCtptIntLot": 126.9217859,
        "MaxStopsePdsgRmdrCs": 1210,
        "protectedMaxAllowedsePdsgRmdrCs": 480
    },
    {
        "itstId": "1307",
        "itstNm": "신도림SK뷰",
        "mapCtptIntLat": 37.5077251,
        "mapCtptIntLot": 126.8864342,
        "NewmapCtptIntLat": 37.5078149,
        "NewmapCtptIntLot": 126.886321,
        "MaxStopnwPdsgRmdrCs": 1240,
        "protectedMaxAllowednwPdsgRmdrCs": 430
    },
    {
        "itstId": "1375",
        "itstNm": "서초롯데캐슬아파트",
        "mapCtptIntLat": 37.5008325,
        "mapCtptIntLot": 127.0223736,
        "NewmapCtptIntLat": 37.5008325,
        "NewmapCtptIntLot": 127.0224868,
        "MaxStopetPdsgRmdrCs": 500,
        "protectedMaxAllowedetPdsgRmdrCs": 350
    },
    {
        "itstId": "1383",
        "itstNm": "안암교",
        "mapCtptIntLat": 37.5770521,
        "mapCtptIntLot": 127.028177,
        "NewmapCtptIntLat": 37.5769623,
        "NewmapCtptIntLot": 127.028177,
        "MaxStopstPdsgRmdrCs": 920,
        "protectedMaxAllowedstPdsgRmdrCs": 370
    },
    {
        "itstId": "1424",
        "itstNm": "교보타워사거리",
        "mapCtptIntLat": 37.5045212,
        "mapCtptIntLot": 127.0244863,
        "NewmapCtptIntLat": 37.5045212,
        "NewmapCtptIntLot": 127.0243731,
        "MaxStopntPdsgRmdrCs": 1250,
        "protectedMaxAllowedntPdsgRmdrCs": 330,
        "MaxStopetPdsgRmdrCs": 1160,
        "protectedMaxAllowedetPdsgRmdrCs": 430,
        "MaxStopstPdsgRmdrCs": 1250,
        "protectedMaxAllowedstPdsgRmdrCs": 330,
        "MaxStopwtPdsgRmdrCs": 1160,
        "protectedMaxAllowedwtPdsgRmdrCs": 430
    },
    {
        "itstId": "1426",
        "itstNm": "산골고개",
        "mapCtptIntLat": 37.5976128,
        "mapCtptIntLot": 126.938609,
        "NewmapCtptIntLat": 37.5976128,
        "NewmapCtptIntLot": 126.9384956,
        "MaxStopwtPdsgRmdrCs": 1220,
        "protectedMaxAllowedwtPdsgRmdrCs": 360
    },
    {
        "itstId": "1446",
        "itstNm": "AT센터",
        "mapCtptIntLat": 37.4686115,
        "mapCtptIntLot": 127.0398477,
        "NewmapCtptIntLat": 37.4685217,
        "NewmapCtptIntLot": 127.0397345,
        "MaxStopsePdsgRmdrCs": 880,
        "protectedMaxAllowedsePdsgRmdrCs": 220,
        "MaxStopswPdsgRmdrCs": 1140,
        "protectedMaxAllowedswPdsgRmdrCs": 450
    },
    {
        "itstId": "1460",
        "itstNm": "개나리아파트정문",
        "mapCtptIntLat": 37.4993609,
        "mapCtptIntLot": 127.0471824,
        "NewmapCtptIntLat": 37.4992711,
        "NewmapCtptIntLot": 127.0471824,
        "MaxStopstPdsgRmdrCs": 1300,
        "protectedMaxAllowedstPdsgRmdrCs": 390
    },
    {
        "itstId": "1463",
        "itstNm": "종로노인복지관앞",
        "mapCtptIntLat": 37.5756133,
        "mapCtptIntLot": 127.0050093,
        "NewmapCtptIntLat": 37.5755235,
        "NewmapCtptIntLot": 127.0051226,
        "protectedMaxAllowednePdsgRmdrCs": 290
    },
    {
        "itstId": "1506",
        "itstNm": "종묘입구",
        "mapCtptIntLat": 37.5726051,
        "mapCtptIntLot": 126.9915319,
        "NewmapCtptIntLat": 37.5726051,
        "NewmapCtptIntLot": 126.9914186,
        "MaxStopntPdsgRmdrCs": 570,
        "protectedMaxAllowedntPdsgRmdrCs": 330,
        "MaxStopetPdsgRmdrCs": 570,
        "protectedMaxAllowedetPdsgRmdrCs": 330,
        "MaxStopstPdsgRmdrCs": 570,
        "protectedMaxAllowedstPdsgRmdrCs": 330,
        "MaxStopwtPdsgRmdrCs": 570,
        "protectedMaxAllowedwtPdsgRmdrCs": 330
    },
    {
        "itstId": "1574",
        "itstNm": "동대문역",
        "mapCtptIntLat": 37.5720141,
        "mapCtptIntLot": 127.0122574,
        "NewmapCtptIntLat": 37.5719243,
        "NewmapCtptIntLot": 127.0122574,
        "MaxStopstPdsgRmdrCs": 1350,
        "protectedMaxAllowedstPdsgRmdrCs": 350
    },
    {
        "itstId": "1611",
        "itstNm": "탑골공원",
        "mapCtptIntLat": 37.5716041,
        "mapCtptIntLot": 126.9876359,
        "NewmapCtptIntLat": 37.5716041,
        "NewmapCtptIntLot": 126.9875226,
        "MaxStopwtPdsgRmdrCs": 940,
        "protectedMaxAllowedwtPdsgRmdrCs": 350
    },
    {
        "itstId": "1620",
        "itstNm": "국일관",
        "mapCtptIntLat": 37.5703027,
        "mapCtptIntLot": 126.9897302,
        "NewmapCtptIntLat": 37.5702129,
        "NewmapCtptIntLot": 126.9897302,
        "MaxStopstPdsgRmdrCs": 1080,
        "protectedMaxAllowedstPdsgRmdrCs": 520
    },
    {
        "itstId": "1648",
        "itstNm": "한전성서지점",
        "mapCtptIntLat": 37.6057415,
        "mapCtptIntLot": 126.9341247,
        "NewmapCtptIntLat": 37.6056517,
        "NewmapCtptIntLot": 126.9340113,
        "MaxStopnePdsgRmdrCs": 1240,
        "protectedMaxAllowednePdsgRmdrCs": 370,
        "MaxStopsePdsgRmdrCs": 1240,
        "protectedMaxAllowedsePdsgRmdrCs": 370,
        "MaxStopswPdsgRmdrCs": 1220,
        "protectedMaxAllowedswPdsgRmdrCs": 370
    },
    {
        "itstId": "1662",
        "itstNm": "가좌역",
        "mapCtptIntLat": 37.5691157,
        "mapCtptIntLot": 126.9152728,
        "NewmapCtptIntLat": 37.5690259,
        "NewmapCtptIntLot": 126.9151595,
        "MaxStopswPdsgRmdrCs": 990,
        "protectedMaxAllowedswPdsgRmdrCs": 410
    },
    {
        "itstId": "1812",
        "itstNm": "신설동역",
        "mapCtptIntLat": 37.5755809,
        "mapCtptIntLot": 127.0232274,
        "NewmapCtptIntLat": 37.5754911,
        "NewmapCtptIntLot": 127.0231141,
        "MaxStopntPdsgRmdrCs": 1560,
        "protectedMaxAllowedntPdsgRmdrCs": 440,
        "MaxStopstPdsgRmdrCs": 1180,
        "protectedMaxAllowedstPdsgRmdrCs": 290,
        "MaxStopnePdsgRmdrCs": 1660,
        "protectedMaxAllowednePdsgRmdrCs": 350,
        "MaxStopswPdsgRmdrCs": 990,
        "protectedMaxAllowedswPdsgRmdrCs": 290
    },
    {
        "itstId": "1814",
        "itstNm": "종로6가",
        "mapCtptIntLat": 37.5711036,
        "mapCtptIntLot": 127.0067086,
        "NewmapCtptIntLat": 37.5711934,
        "NewmapCtptIntLot": 127.0067086,
        "MaxStopntPdsgRmdrCs": 980,
        "protectedMaxAllowedntPdsgRmdrCs": 410
    },
    {
        "itstId": "1816",
        "itstNm": "종로4가",
        "mapCtptIntLat": 37.5707425,
        "mapCtptIntLot": 126.9977692,
        "NewmapCtptIntLat": 37.5706527,
        "NewmapCtptIntLot": 126.9977692,
        "MaxStopstPdsgRmdrCs": 970,
        "protectedMaxAllowedstPdsgRmdrCs": 410
    },
    {
        "itstId": "1817",
        "itstNm": "종로구청입구",
        "mapCtptIntLat": 37.5702029,
        "mapCtptIntLot": 126.9793148,
        "NewmapCtptIntLat": 37.5702029,
        "NewmapCtptIntLot": 126.9792015,
        "protectedMaxAllowedntPdsgRmdrCs": 550,
        "protectedMaxAllowedetPdsgRmdrCs": 550,
        "protectedMaxAllowedstPdsgRmdrCs": 550,
        "protectedMaxAllowedwtPdsgRmdrCs": 550
    },
    {
        "itstId": "1818",
        "itstNm": "종로백화점약국",
        "mapCtptIntLat": 37.5710408,
        "mapCtptIntLot": 127.0037626,
        "NewmapCtptIntLat": 37.570951,
        "NewmapCtptIntLot": 127.0037626,
        "MaxStopstPdsgRmdrCs": 1000,
        "protectedMaxAllowedstPdsgRmdrCs": 400
    },
    {
        "itstId": "1819",
        "itstNm": "종로1가",
        "mapCtptIntLat": 37.5702264,
        "mapCtptIntLot": 126.9829758,
        "etmapCtptIntLat": 37.5702264,
        "etmapCtptIntLot":  126.9831358,
        "NewmapCtptIntLat": 37.5702264,
        "NewmapCtptIntLot": 126.9828625,
        "MaxStopntPdsgRmdrCs": 1180,
        "protectedMaxAllowedntPdsgRmdrCs": 420,
        "MaxStopetPdsgRmdrCs": 1180,
        "protectedMaxAllowedetPdsgRmdrCs": 420,
        "MaxStopstPdsgRmdrCs": 1180,
        "protectedMaxAllowedstPdsgRmdrCs": 420,
        "MaxStopwtPdsgRmdrCs": 1180,
        "protectedMaxAllowedwtPdsgRmdrCs": 420
    },
    {
        "itstId": "1820",
        "itstNm": "종로2가",
        "mapCtptIntLat": 37.5702056,
        "mapCtptIntLot": 126.9876851,
        "ntmapCtptIntLat": 37.5704556,
        "ntmapCtptIntLot": 126.9876851,
        "etmapCtptIntLat": 37.5702256,
        "etmapCtptIntLot": 126.9881451,
        "wtmapCtptIntLat": 37.5702056,
        "wtmapCtptIntLot": 126.9873551,
        "stmapCtptIntLat": 37.5699056,
        "stmapCtptIntLot": 126.9877051,
        "NewmapCtptIntLat": 37.5702056,
        "NewmapCtptIntLot": 126.9875718,
        "MaxStopntPdsgRmdrCs": 1170,
        "protectedMaxAllowedntPdsgRmdrCs": 420,
        "MaxStopetPdsgRmdrCs": 1200,
        "protectedMaxAllowedetPdsgRmdrCs": 400,
        "MaxStopstPdsgRmdrCs": 1130,
        "protectedMaxAllowedstPdsgRmdrCs": 470,
        "MaxStopwtPdsgRmdrCs": 1200,
        "protectedMaxAllowedwtPdsgRmdrCs": 400
    },
    {
        "itstId": "1826",
        "itstNm": "안국역",
        "mapCtptIntLat": 37.5768589,
        "mapCtptIntLot": 126.9861801,
        "NewmapCtptIntLat": 37.5767691,
        "NewmapCtptIntLot": 126.9860668,
        "MaxStopntPdsgRmdrCs": 1280,
        "MaxStopstPdsgRmdrCs": 1280,
        "protectedMaxAllowednePdsgRmdrCs": 370,
        "protectedMaxAllowedswPdsgRmdrCs": 370
    },
    {
        "itstId": "1830",
        "itstNm": "재향군인회",
        "mapCtptIntLat": 37.5733612,
        "mapCtptIntLot": 126.9975784,
        "NewmapCtptIntLat": 37.5733612,
        "NewmapCtptIntLot": 126.9974651,
        "protectedMaxAllowedetPdsgRmdrCs": 350,
        "protectedMaxAllowedstPdsgRmdrCs": 350,
        "protectedMaxAllowedwtPdsgRmdrCs": 350
    },
    {
        "itstId": "1831",
        "itstNm": "혜화역",
        "mapCtptIntLat": 37.5829472,
        "mapCtptIntLot": 127.001763,
        "NewmapCtptIntLat": 37.5829472,
        "NewmapCtptIntLot": 127.0016496,
        "protectedMaxAllowedwtPdsgRmdrCs": 360
    },
    {
        "itstId": "1832",
        "itstNm": "무악재역",
        "mapCtptIntLat": 37.5819776,
        "mapCtptIntLot": 126.9505189,
        "NewmapCtptIntLat": 37.5818878,
        "NewmapCtptIntLot": 126.9504055,
        "MaxStopswPdsgRmdrCs": 1430,
        "protectedMaxAllowedswPdsgRmdrCs": 380
    },
    {
        "itstId": "1835",
        "itstNm": "광교",
        "mapCtptIntLat": 37.5690373,
        "mapCtptIntLot": 126.9827797,
        "ntmapCtptIntLat": 37.5691673,
        "ntmapCtptIntLot": 126.9828097,
        "etmapCtptIntLat": 37.5690273,
        "etmapCtptIntLot": 126.9830297,
        "wtmapCtptIntLat": 37.5690673,
        "wtmapCtptIntLot": 126.9824997,
        "NewmapCtptIntLat": 37.5689475,
        "NewmapCtptIntLot": 126.9827797,
        "MaxStopntPdsgRmdrCs": 420,
        "MaxStopetPdsgRmdrCs": 420,
        "MaxStopwtPdsgRmdrCs": 420,
        "protectedMaxAllowedntPdsgRmdrCs": 380,
        "protectedMaxAllowedetPdsgRmdrCs": 380,
        "protectedMaxAllowedwtPdsgRmdrCs": 380
    },
    {
        "itstId": "1839",
        "itstNm": "종로5가",
        "mapCtptIntLat": 37.5710013,
        "mapCtptIntLot": 127.0019255,
        "NewmapCtptIntLat": 37.5710013,
        "NewmapCtptIntLot": 127.0018122,
        "MaxStopetPdsgRmdrCs": 1010,
        "protectedMaxAllowedetPdsgRmdrCs": 370,
        "MaxStopwtPdsgRmdrCs": 1010,
        "protectedMaxAllowedwtPdsgRmdrCs": 370
    },
    {
        "itstId": "1843",
        "itstNm": "낙원상가",
        "mapCtptIntLat": 37.5735455,
        "mapCtptIntLot": 126.9876807,
        "NewmapCtptIntLat": 37.5735455,
        "NewmapCtptIntLot": 126.987794,
        "protectedMaxAllowedetPdsgRmdrCs": 440
    },
    {
        "itstId": "1850",
        "itstNm": "청계2가",
        "mapCtptIntLat": 37.5682795,
        "mapCtptIntLot": 126.9876861,
        "ntmapCtptIntLat": 37.5684695, 
        "ntmapCtptIntLot": 126.9876461,
        "etmapCtptIntLat": 37.5682995, 
        "etmapCtptIntLot": 126.9878661,
        "wtmapCtptIntLat": 37.5683295, 
        "wtmapCtptIntLot": 126.9874361,
        "NewmapCtptIntLat": 37.5681897,
        "NewmapCtptIntLot": 126.9876861,
        "MaxStopntPdsgRmdrCs": 420,
        "MaxStopetPdsgRmdrCs": 420,
        "MaxStopwtPdsgRmdrCs": 420,
        "protectedMaxAllowedntPdsgRmdrCs": 380,
        "protectedMaxAllowedetPdsgRmdrCs": 380,
        "protectedMaxAllowedwtPdsgRmdrCs": 380
    },
    {
        "itstId": "1851",
        "itstNm": "창경궁",
        "mapCtptIntLat": 37.5790415,
        "mapCtptIntLot": 126.9966823,
        "NewmapCtptIntLat": 37.5790415,
        "NewmapCtptIntLot": 126.9967957,
        "MaxStopetPdsgRmdrCs": 1050,
        "protectedMaxAllowedetPdsgRmdrCs": 350
    },
    {
        "itstId": "1854",
        "itstNm": "조계사",
        "mapCtptIntLat": 37.5739436,
        "mapCtptIntLot": 126.9829375,
        "NewmapCtptIntLat": 37.5739436,
        "NewmapCtptIntLot": 126.9828242,
        "MaxStopwtPdsgRmdrCs": 1060,
        "protectedMaxAllowedwtPdsgRmdrCs": 330
    },
    {
        "itstId": "1857",
        "itstNm": "정부서울청사",
        "mapCtptIntLat": 37.575758,
        "mapCtptIntLot": 126.9743313,
        "NewmapCtptIntLat": 37.575758,
        "NewmapCtptIntLot": 126.9744446,
        "protectedMaxAllowedetPdsgRmdrCs": 410
    },
    {
        "itstId": "1863",
        "itstNm": "종로3가",
        "mapCtptIntLat": 37.5704205,
        "mapCtptIntLot": 126.9921386,
        "ntmapCtptIntLat": 37.5707205, 
        "ntmapCtptIntLot": 126.9921086,
        "etmapCtptIntLat": 37.5704405, 
        "etmapCtptIntLot": 126.9923386,
        "wtmapCtptIntLat": 37.5704205, 
        "wtmapCtptIntLot": 126.9919386,
        "stmapCtptIntLat": 37.5702905,
        "stmapCtptIntLot": 126.9921386,
        "MaxStopntPdsgRmdrCs": 1200,
        "protectedMaxAllowedntPdsgRmdrCs": 800,
        "MaxStopetPdsgRmdrCs": 1200,
        "protectedMaxAllowedetPdsgRmdrCs": 800,
        "MaxStopstPdsgRmdrCs": 1200,
        "protectedMaxAllowedstPdsgRmdrCs": 800,
        "MaxStopwtPdsgRmdrCs": 1200,
        "protectedMaxAllowedwtPdsgRmdrCs": 800,
        "NewmapCtptIntLat": 37.5704205,
        "NewmapCtptIntLot": 126.9921385
    },
    {
        "itstId": "1864",
        "itstNm": "청계4가",
        "mapCtptIntLat": 37.5690316,
        "mapCtptIntLot": 126.9979233,
        "NewmapCtptIntLat": 37.5689418,
        "NewmapCtptIntLot": 126.9979233,
        "MaxStopntPdsgRmdrCs": 410,
        "protectedMaxAllowedntPdsgRmdrCs": 260,
        "MaxStopstPdsgRmdrCs": 410,
        "protectedMaxAllowedstPdsgRmdrCs": 260
    },
    {
        "itstId": "1865",
        "itstNm": "동묘앞역",
        "mapCtptIntLat": 37.5730228,
        "mapCtptIntLot": 127.0156343,
        "NewmapCtptIntLat": 37.572933,
        "NewmapCtptIntLot": 127.015521,
        "protectedMaxAllowedntPdsgRmdrCs": 340,
        "protectedMaxAllowedstPdsgRmdrCs": 340,
        "protectedMaxAllowednePdsgRmdrCs": 310,
        "protectedMaxAllowedswPdsgRmdrCs": 310
    },
    {
        "itstId": "1866",
        "itstNm": "성균관대입구",
        "mapCtptIntLat": 37.5830166,
        "mapCtptIntLot": 126.9987504,
        "NewmapCtptIntLat": 37.5831064,
        "NewmapCtptIntLot": 126.998637,
        "MaxStopnePdsgRmdrCs": 1050,
        "protectedMaxAllowednePdsgRmdrCs": 350,
        "MaxStopsePdsgRmdrCs": 1050,
        "protectedMaxAllowedsePdsgRmdrCs": 350,
        "MaxStopnwPdsgRmdrCs": 1050,
        "protectedMaxAllowednwPdsgRmdrCs": 350
    },
    {
        "itstId": "1867",
        "itstNm": "국립과학관",
        "mapCtptIntLat": 37.5814946,
        "mapCtptIntLot": 126.9970056,
        "NewmapCtptIntLat": 37.5814048,
        "NewmapCtptIntLot": 126.997119,
        "MaxStopsePdsgRmdrCs": 1040,
        "protectedMaxAllowedsePdsgRmdrCs": 360
    },
    {
        "itstId": "1921",
        "itstNm": "삼일빌딩앞",
        "mapCtptIntLat": 37.5627074,
        "mapCtptIntLot": 127.0003211,
        "NewmapCtptIntLat": 37.5626176,
        "NewmapCtptIntLot": 127.0004344,
        "MaxStopsePdsgRmdrCs": 1070,
        "protectedMaxAllowedsePdsgRmdrCs": 320
    },
    {
        "itstId": "1922",
        "itstNm": "홍은풍림아파트",
        "mapCtptIntLat": 37.595159,
        "mapCtptIntLot": 126.9402854,
        "NewmapCtptIntLat": 37.5950692,
        "NewmapCtptIntLot": 126.940172,
        "MaxStopswPdsgRmdrCs": 1200,
        "protectedMaxAllowedswPdsgRmdrCs": 390
    },
    {
        "itstId": "1923",
        "itstNm": "홍제역",
        "mapCtptIntLat": 37.5880055,
        "mapCtptIntLot": 126.9451089,
        "NewmapCtptIntLat": 37.5879157,
        "NewmapCtptIntLot": 126.9449955,
        "protectedMaxAllowedswPdsgRmdrCs": 380
    },
    {
        "itstId": "1926",
        "itstNm": "안산초교",
        "mapCtptIntLat": 37.5805804,
        "mapCtptIntLot": 126.9517861,
        "NewmapCtptIntLat": 37.5806702,
        "NewmapCtptIntLot": 126.9518995,
        "MaxStopnePdsgRmdrCs": 1400,
        "protectedMaxAllowednePdsgRmdrCs": 400
    },
    {
        "itstId": "1971",
        "itstNm": "평안섬유공업사",
        "mapCtptIntLat": 37.5891509,
        "mapCtptIntLot": 127.0589138,
        "NewmapCtptIntLat": 37.5890611,
        "NewmapCtptIntLot": 127.0589138,
        "MaxStopstPdsgRmdrCs": 1140,
        "protectedMaxAllowedstPdsgRmdrCs": 360
    },
    {
        "itstId": "1999",
        "itstNm": "원남동사거리",
        "mapCtptIntLat": 37.5759134,
        "mapCtptIntLot": 126.9973494,
        "NewmapCtptIntLat": 37.5760032,
        "NewmapCtptIntLot": 126.9972361,
        "MaxStopntPdsgRmdrCs": 1560,
        "protectedMaxAllowedntPdsgRmdrCs": 360,
        "MaxStopetPdsgRmdrCs": 1590,
        "protectedMaxAllowedetPdsgRmdrCs": 300,
        "MaxStopstPdsgRmdrCs": 1600,
        "protectedMaxAllowedstPdsgRmdrCs": 280,
        "MaxStopnwPdsgRmdrCs": 1650,
        "protectedMaxAllowednwPdsgRmdrCs": 250
    },
    {
        "itstId": "2117",
        "itstNm": "한남오거리",
        "mapCtptIntLat": 37.5333663,
        "mapCtptIntLot": 127.0076873,
        "NewmapCtptIntLat": 37.5334561,
        "NewmapCtptIntLot": 127.007574,
        "protectedMaxAllowednePdsgRmdrCs": 490,
        "MaxStopsePdsgRmdrCs": 1790,
        "protectedMaxAllowedswPdsgRmdrCs": 470,
        "MaxStopnwPdsgRmdrCs": 1790
    },
    {
        "itstId": "2203",
        "itstNm": "논현역",
        "mapCtptIntLat": 37.5111134,
        "mapCtptIntLot": 127.0213298,
        "NewmapCtptIntLat": 37.5110236,
        "NewmapCtptIntLot": 127.0213298,
        "MaxStopntPdsgRmdrCs": 1450,
        "protectedMaxAllowedntPdsgRmdrCs": 350,
        "MaxStopstPdsgRmdrCs": 1450,
        "protectedMaxAllowedstPdsgRmdrCs": 350
    },
    {
        "itstId": "2207",
        "itstNm": "국기원입구",
        "mapCtptIntLat": 37.4990121,
        "mapCtptIntLot": 127.0310323,
        "NewmapCtptIntLat": 37.4990121,
        "NewmapCtptIntLot": 127.0309191,
        "MaxStopntPdsgRmdrCs": 1220,
        "protectedMaxAllowedntPdsgRmdrCs": 350,
        "MaxStopetPdsgRmdrCs": 860,
        "protectedMaxAllowedetPdsgRmdrCs": 230,
        "MaxStopstPdsgRmdrCs": 1220,
        "protectedMaxAllowedstPdsgRmdrCs": 350,
        "MaxStopwtPdsgRmdrCs": 1300,
        "protectedMaxAllowedwtPdsgRmdrCs": 300
    },
    {
        "itstId": "2212",
        "itstNm": "선릉역",
        "mapCtptIntLat": 37.5044875,
        "mapCtptIntLot": 127.0490277,
        "NewmapCtptIntLat": 37.5044875,
        "NewmapCtptIntLot": 127.0489145,
        "MaxStopntPdsgRmdrCs": 820,
        "protectedMaxAllowedntPdsgRmdrCs": 730,
        "MaxStopetPdsgRmdrCs": 1270,
        "protectedMaxAllowedetPdsgRmdrCs": 300,
        "MaxStopstPdsgRmdrCs": 820,
        "protectedMaxAllowedstPdsgRmdrCs": 730,
        "MaxStopwtPdsgRmdrCs": 1270,
        "protectedMaxAllowedwtPdsgRmdrCs": 300
    },
    {
        "itstId": "2214",
        "itstNm": "포스코사거리",
        "mapCtptIntLat": 37.5068692,
        "mapCtptIntLot": 127.0566375,
        "NewmapCtptIntLat": 37.506959,
        "NewmapCtptIntLot": 127.0565243,
        "MaxStopetPdsgRmdrCs": 1180,
        "protectedMaxAllowedetPdsgRmdrCs": 420,
        "MaxStopwtPdsgRmdrCs": 1180,
        "protectedMaxAllowedwtPdsgRmdrCs": 420,
        "MaxStopsePdsgRmdrCs": 1170,
        "protectedMaxAllowedsePdsgRmdrCs": 430,
        "MaxStopnwPdsgRmdrCs": 1170,
        "protectedMaxAllowednwPdsgRmdrCs": 430
    },
    {
        "itstId": "2215",
        "itstNm": "현대백화점무역센터",
        "mapCtptIntLat": 37.507738,
        "mapCtptIntLot": 127.0594374,
        "NewmapCtptIntLat": 37.5076482,
        "NewmapCtptIntLot": 127.0594374,
        "MaxStopntPdsgRmdrCs": 2550,
        "protectedMaxAllowedntPdsgRmdrCs": 450,
        "MaxStopetPdsgRmdrCs": 1250,
        "protectedMaxAllowedetPdsgRmdrCs": 2550,
        "MaxStopstPdsgRmdrCs": 2550,
        "protectedMaxAllowedstPdsgRmdrCs": 450
    },
    {
        "itstId": "2216",
        "itstNm": "원혜빌딩",
        "mapCtptIntLat": 37.5084538,
        "mapCtptIntLot": 127.0557904,
        "NewmapCtptIntLat": 37.5085436,
        "NewmapCtptIntLot": 127.0559036,
        "MaxStopntPdsgRmdrCs": 700,
        "protectedMaxAllowedntPdsgRmdrCs": 330,
        "MaxStopstPdsgRmdrCs": 700,
        "protectedMaxAllowedstPdsgRmdrCs": 330,
        "MaxStopnePdsgRmdrCs": 1310,
        "protectedMaxAllowednePdsgRmdrCs": 280
    },
    {
        "itstId": "2217",
        "itstNm": "역삼역",
        "mapCtptIntLat": 37.500825,
        "mapCtptIntLot": 127.0369311,
        "NewmapCtptIntLat": 37.500825,
        "NewmapCtptIntLot": 127.0368179,
        "MaxStopntPdsgRmdrCs": 1100,
        "protectedMaxAllowedntPdsgRmdrCs": 480,
        "MaxStopetPdsgRmdrCs": 1230,
        "protectedMaxAllowedetPdsgRmdrCs": 380,
        "MaxStopstPdsgRmdrCs": 1100,
        "protectedMaxAllowedstPdsgRmdrCs": 480,
        "MaxStopwtPdsgRmdrCs": 1230,
        "protectedMaxAllowedwtPdsgRmdrCs": 380
    },
    {
        "itstId": "2219",
        "itstNm": "르네상스호텔",
        "mapCtptIntLat": 37.5026162,
        "mapCtptIntLot": 127.0427921,
        "NewmapCtptIntLat": 37.5026162,
        "NewmapCtptIntLot": 127.0426789,
        "MaxStopntPdsgRmdrCs": 2550,
        "protectedMaxAllowedntPdsgRmdrCs": 2550,
        "MaxStopetPdsgRmdrCs": 2550,
        "protectedMaxAllowedetPdsgRmdrCs": 2550,
        "MaxStopstPdsgRmdrCs": 2550,
        "protectedMaxAllowedstPdsgRmdrCs": 2550,
        "MaxStopwtPdsgRmdrCs": 2550,
        "protectedMaxAllowedwtPdsgRmdrCs": 2550
    },
    {
        "itstId": "2229",
        "itstNm": "서교동사거리",
        "mapCtptIntLat": 37.5527275,
        "mapCtptIntLot": 126.9182087,
        "NewmapCtptIntLat": 37.5528173,
        "NewmapCtptIntLot": 126.9180954,
        "MaxStopnePdsgRmdrCs": 1460,
        "protectedMaxAllowednePdsgRmdrCs": 230,
        "MaxStopsePdsgRmdrCs": 1360,
        "protectedMaxAllowedsePdsgRmdrCs": 330,
        "MaxStopswPdsgRmdrCs": 1460,
        "protectedMaxAllowedswPdsgRmdrCs": 230,
        "MaxStopnwPdsgRmdrCs": 1310,
        "protectedMaxAllowednwPdsgRmdrCs": 380
    },
    {
        "itstId": "2231",
        "itstNm": "월드컵파크207동",
        "mapCtptIntLat": 37.5759707,
        "mapCtptIntLot": 126.8911531,
        "NewmapCtptIntLat": 37.5760605,
        "NewmapCtptIntLot": 126.8910398,
        "MaxStopnwPdsgRmdrCs": 640,
        "protectedMaxAllowednwPdsgRmdrCs": 360
    },
    {
        "itstId": "2261",
        "itstNm": "신촌현대백화점",
        "mapCtptIntLat": 37.5560943,
        "mapCtptIntLot": 126.9342876,
        "NewmapCtptIntLat": 37.5560045,
        "NewmapCtptIntLot": 126.9341743,
        "MaxStopswPdsgRmdrCs": 1130,
        "protectedMaxAllowedswPdsgRmdrCs": 450
    },
    {
        "itstId": "2262",
        "itstNm": "안국동사거리",
        "mapCtptIntLat": 37.5756094,
        "mapCtptIntLot": 126.9830054,
        "NewmapCtptIntLat": 37.5756992,
        "NewmapCtptIntLot": 126.9831187,
        "MaxStopstPdsgRmdrCs": 1220,
        "protectedMaxAllowedstPdsgRmdrCs": 380,
        "MaxStopnePdsgRmdrCs": 1020,
        "protectedMaxAllowednePdsgRmdrCs": 570
    },
    {
        "itstId": "2264",
        "itstNm": "동부시장",
        "mapCtptIntLat": 37.5942133,
        "mapCtptIntLot": 127.077249,
        "NewmapCtptIntLat": 37.5943031,
        "NewmapCtptIntLot": 127.0771356,
        "MaxStopetPdsgRmdrCs": 1220,
        "protectedMaxAllowedetPdsgRmdrCs": 380,
        "MaxStopwtPdsgRmdrCs": 530,
        "protectedMaxAllowedwtPdsgRmdrCs": 310,
        "MaxStopsePdsgRmdrCs": 530,
        "protectedMaxAllowedsePdsgRmdrCs": 310,
        "MaxStopnwPdsgRmdrCs": 1220,
        "protectedMaxAllowednwPdsgRmdrCs": 380
    },
    {
        "itstId": "2287",
        "itstNm": "베네치아호텔",
        "mapCtptIntLat": 37.5060268,
        "mapCtptIntLot": 127.0344866,
        "NewmapCtptIntLat": 37.5060268,
        "NewmapCtptIntLot": 127.0343734,
        "MaxStopwtPdsgRmdrCs": 1220,
        "protectedMaxAllowedwtPdsgRmdrCs": 290
    },
    {
        "itstId": "2290",
        "itstNm": "선릉공원앞",
        "mapCtptIntLat": 37.5070125,
        "mapCtptIntLot": 127.0471447,
        "NewmapCtptIntLat": 37.5069227,
        "NewmapCtptIntLot": 127.0470315,
        "MaxStopsePdsgRmdrCs": 400,
        "protectedMaxAllowedsePdsgRmdrCs": 420,
        "MaxStopswPdsgRmdrCs": 1330,
        "protectedMaxAllowedswPdsgRmdrCs": 280
    },
    {
        "itstId": "20035",
        "itstNm": "전기공제회관(연등)",
        "mapCtptIntLat": 37.514299,
        "mapCtptIntLot": 127.0201207,
        "NewmapCtptIntLat": 37.514299,
        "NewmapCtptIntLot": 127.020234,
        "MaxStopetPdsgRmdrCs": 1250,
        "protectedMaxAllowedetPdsgRmdrCs": 540
    },
    {
        "itstId": "20077",
        "itstNm": "롯데백화점도곡(연등)",
        "mapCtptIntLat": 37.4973799,
        "mapCtptIntLot": 127.0562029,
        "NewmapCtptIntLat": 37.4974697,
        "NewmapCtptIntLot": 127.0562029,
        "MaxStopntPdsgRmdrCs": 2550,
        "protectedMaxAllowedntPdsgRmdrCs": 2550
    },
    {
        "itstId": "20109",
        "itstNm": "서초삼성스위트아파트(연등)",
        "mapCtptIntLat": 37.4940062,
        "mapCtptIntLot": 127.0256325,
        "NewmapCtptIntLat": 37.4940062,
        "NewmapCtptIntLot": 127.0257457,
        "MaxStopetPdsgRmdrCs": 640,
        "protectedMaxAllowedetPdsgRmdrCs": 220
    },
    {
        "itstId": "20158",
        "itstNm": "청계6가(연등)",
        "mapCtptIntLat": 37.569639,
        "mapCtptIntLot": 127.0097319,
        "NewmapCtptIntLat": 37.5695492,
        "NewmapCtptIntLot": 127.0097319,
        "MaxStopntPdsgRmdrCs": 620,
        "protectedMaxAllowedntPdsgRmdrCs": 500,
        "MaxStopstPdsgRmdrCs": 1200,
        "protectedMaxAllowedstPdsgRmdrCs": 500
    },
    {
        "itstId": "20160",
        "itstNm": "삼성힐스테이트2단지앞(연등)",
        "mapCtptIntLat": 37.5119827,
        "mapCtptIntLot": 127.0496803,
        "NewmapCtptIntLat": 37.5118929,
        "NewmapCtptIntLot": 127.0496803,
        "MaxStopstPdsgRmdrCs": 1220,
        "protectedMaxAllowedstPdsgRmdrCs": 380
    },
    {
        "itstId": "20406",
        "itstNm": "삼양입구사거리(연등)1",
        "mapCtptIntLat": 37.616641,
        "mapCtptIntLot": 127.029846,
        "NewmapCtptIntLat": 37.616641,
        "NewmapCtptIntLot": 127.0299594,
        "MaxStopetPdsgRmdrCs": 1280,
        "protectedMaxAllowedetPdsgRmdrCs": 320
    },
    {
        "itstId": "20408",
        "itstNm": "도봉세무서(연등)",
        "mapCtptIntLat": 37.6189823,
        "mapCtptIntLot": 127.0290591,
        "NewmapCtptIntLat": 37.6190721,
        "NewmapCtptIntLot": 127.0291725,
        "MaxStopnePdsgRmdrCs": 1240,
        "protectedMaxAllowednePdsgRmdrCs": 360
    },
    {
        "itstId": "20409",
        "itstNm": "방송대북부별관(연등)",
        "mapCtptIntLat": 37.6207067,
        "mapCtptIntLot": 127.0284102,
        "NewmapCtptIntLat": 37.6206169,
        "NewmapCtptIntLot": 127.0282968,
        "MaxStopswPdsgRmdrCs": 1290,
        "protectedMaxAllowedswPdsgRmdrCs": 290
    },
    {
        "itstId": "20410",
        "itstNm": "미아역(연등)",
        "mapCtptIntLat": 37.6271499,
        "mapCtptIntLot": 127.025859,
        "NewmapCtptIntLat": 37.6272397,
        "NewmapCtptIntLot": 127.0259724,
        "MaxStopnePdsgRmdrCs": 1240,
        "protectedMaxAllowednePdsgRmdrCs": 360
    },
    {
        "itstId": "20423",
        "itstNm": "수유3동우체국(연등)",
        "mapCtptIntLat": 37.642193,
        "mapCtptIntLot": 127.030145,
        "NewmapCtptIntLat": 37.6421032,
        "NewmapCtptIntLot": 127.0302584,
        "MaxStopsePdsgRmdrCs": 1230,
        "protectedMaxAllowedsePdsgRmdrCs": 360
    },
    {
        "itstId": "20470",
        "itstNm": "불광역(연등)",
        "mapCtptIntLat": 37.6121223,
        "mapCtptIntLot": 126.9285246,
        "NewmapCtptIntLat": 37.6122121,
        "NewmapCtptIntLot": 126.928638,
        "MaxStopnePdsgRmdrCs": 1260,
        "protectedMaxAllowednePdsgRmdrCs": 330
    },
    {
        "itstId": "20643",
        "itstNm": "미아서광빌딩(연등)",
        "mapCtptIntLat": 37.6231767,
        "mapCtptIntLot": 127.0274346,
        "NewmapCtptIntLat": 37.6230869,
        "NewmapCtptIntLot": 127.0273212,
        "MaxStopswPdsgRmdrCs": 1200,
        "protectedMaxAllowedswPdsgRmdrCs": 400
    },
    {
        "itstId": "20644",
        "itstNm": "숭인시장(연등)",
        "mapCtptIntLat": 37.6132158,
        "mapCtptIntLot": 127.0300703,
        "NewmapCtptIntLat": 37.6132158,
        "NewmapCtptIntLot": 127.0299569,
        "MaxStopwtPdsgRmdrCs": 1290,
        "protectedMaxAllowedwtPdsgRmdrCs": 400
    },
    {
        "itstId": "20648",
        "itstNm": "한성대(연등)1",
        "mapCtptIntLat": 37.5907561,
        "mapCtptIntLot": 127.0111831,
        "NewmapCtptIntLat": 37.5906663,
        "NewmapCtptIntLot": 127.0112965,
        "MaxStopsePdsgRmdrCs": 1200,
        "protectedMaxAllowedsePdsgRmdrCs": 400
    },
    {
        "itstId": "20748",
        "itstNm": "신한은행갈현(연등)",
        "mapCtptIntLat": 37.624681,
        "mapCtptIntLot": 126.919969,
        "NewmapCtptIntLat": 37.624681,
        "NewmapCtptIntLot": 126.9200824,
        "MaxStopetPdsgRmdrCs": 1180,
        "protectedMaxAllowedetPdsgRmdrCs": 410
    },
    {
        "itstId": "20938",
        "itstNm": "오장동사거리(연등)",
        "mapCtptIntLat": 37.5656491,
        "mapCtptIntLot": 127.0024434,
        "NewmapCtptIntLat": 37.5656491,
        "NewmapCtptIntLot": 127.0025567,
        "protectedMaxAllowedetPdsgRmdrCs": 420
    },
    {
        "itstId": "20985",
        "itstNm": "한성대입구역(연등)1",
        "mapCtptIntLat": 37.5876754,
        "mapCtptIntLot": 127.0040161,
        "NewmapCtptIntLat": 37.5875856,
        "NewmapCtptIntLot": 127.0041295,
        "MaxStopsePdsgRmdrCs": 1280,
        "protectedMaxAllowedsePdsgRmdrCs": 280
    },
    {
        "itstId": "21168",
        "itstNm": "길음역(연등)1",
        "mapCtptIntLat": 37.6039261,
        "mapCtptIntLot": 127.024734,
        "NewmapCtptIntLat": 37.6038363,
        "NewmapCtptIntLot": 127.0248474,
        "MaxStopsePdsgRmdrCs": 1260,
        "protectedMaxAllowedsePdsgRmdrCs": 340
    },
    {
        "itstId": "21219",
        "itstNm": "홍대역2번출구(연등)",
        "mapCtptIntLat": 37.5572065,
        "mapCtptIntLot": 126.9242219,
        "NewmapCtptIntLat": 37.5572963,
        "NewmapCtptIntLot": 126.9241086,
        "MaxStopnwPdsgRmdrCs": 1200,
        "protectedMaxAllowednwPdsgRmdrCs": 490
    },
    {
        "itstId": "21375",
        "itstNm": "서초롯데캐슬아파트(연등)",
        "mapCtptIntLat": 37.4999125,
        "mapCtptIntLot": 127.0228049,
        "NewmapCtptIntLat": 37.4999125,
        "NewmapCtptIntLot": 127.0229181,
        "MaxStopetPdsgRmdrCs": 490,
        "protectedMaxAllowedetPdsgRmdrCs": 340
    },
    {
        "itstId": "21611",
        "itstNm": "탑골공원(연등)",
        "mapCtptIntLat": 37.572692,
        "mapCtptIntLot": 126.9878389,
        "NewmapCtptIntLat": 37.572692,
        "NewmapCtptIntLot": 126.9877256,
        "MaxStopntPdsgRmdrCs": 840,
        "protectedMaxAllowedntPdsgRmdrCs": 460,
        "MaxStopetPdsgRmdrCs": 1010,
        "protectedMaxAllowedetPdsgRmdrCs": 290,
        "MaxStopwtPdsgRmdrCs": 1010,
        "protectedMaxAllowedwtPdsgRmdrCs": 290
    },
    {
        "itstId": "21816",
        "itstNm": "종로4가(연등)1",
        "mapCtptIntLat": 37.5701474,
        "mapCtptIntLot": 126.9978832,
        "NewmapCtptIntLat": 37.5701474,
        "NewmapCtptIntLot": 126.9979965,
        "MaxStopetPdsgRmdrCs": 1050,
        "protectedMaxAllowedetPdsgRmdrCs": 350
    },
    {
        "itstId": "21830",
        "itstNm": "재향군인회(연등)",
        "mapCtptIntLat": 37.574215,
        "mapCtptIntLot": 126.997577,
        "NewmapCtptIntLat": 37.574215,
        "NewmapCtptIntLot": 126.9974637,
        "protectedMaxAllowedwtPdsgRmdrCs": 350
    },
    {
        "itstId": "21831",
        "itstNm": "혜화역(연등)1",
        "mapCtptIntLat": 37.5838473,
        "mapCtptIntLot": 127.0016025,
        "NewmapCtptIntLat": 37.5838473,
        "NewmapCtptIntLot": 127.0014891,
        "protectedMaxAllowedwtPdsgRmdrCs": 360
    },
    {
        "itstId": "21835",
        "itstNm": "광교(연등)",
        "mapCtptIntLat": 37.5687245,
        "mapCtptIntLot": 126.9827649,
        "etmapCtptIntLat": 37.5686545,
        "etmapCtptIntLot":  126.9829849,
        "NewmapCtptIntLat": 37.5687245,
        "NewmapCtptIntLot": 126.9826516,
        "MaxStopetPdsgRmdrCs": 420,
        "MaxStopstPdsgRmdrCs": 420,
        "MaxStopwtPdsgRmdrCs": 1200,
        "protectedMaxAllowedetPdsgRmdrCs": 380,
        "protectedMaxAllowedstPdsgRmdrCs": 380,
        "protectedMaxAllowedwtPdsgRmdrCs": 380
    },
    {
        "itstId": "21850",
        "itstNm": "청계2가(연등)",
        "mapCtptIntLat": 37.5679802,
        "mapCtptIntLot": 126.9876671,
        "stmapCtptIntLat": 37.5678802, 
        "stmapCtptIntLot": 126.9876671,
        "etmapCtptIntLat": 37.5679602, 
        "etmapCtptIntLot": 126.9878961,
        "wtmapCtptIntLat": 37.5679802, 
        "wtmapCtptIntLot": 126.9874361,
        "NewmapCtptIntLat": 37.5679802,
        "NewmapCtptIntLot": 126.9875538,
        "MaxStopstPdsgRmdrCs": 420,
        "MaxStopetPdsgRmdrCs": 420,
        "MaxStopwtPdsgRmdrCs": 420,
        "protectedMaxAllowedstPdsgRmdrCs": 380,
        "protectedMaxAllowedetPdsgRmdrCs": 380,
        "protectedMaxAllowedwtPdsgRmdrCs": 380
    },
    {
        "itstId": "21857",
        "itstNm": "정부서울청사(연등)",
        "mapCtptIntLat": 37.5758331,
        "mapCtptIntLot": 126.973606,
        "NewmapCtptIntLat": 37.5759229,
        "NewmapCtptIntLot": 126.973606,
        "protectedMaxAllowedntPdsgRmdrCs": 380
    },
    {
        "itstId": "21864",
        "itstNm": "청계4가(연등)",
        "mapCtptIntLat": 37.5687441,
        "mapCtptIntLot": 126.9979823,
        "NewmapCtptIntLat": 37.5687441,
        "NewmapCtptIntLot": 126.997869,
        "MaxStopntPdsgRmdrCs": 440,
        "protectedMaxAllowedntPdsgRmdrCs": 290,
        "MaxStopetPdsgRmdrCs": 440,
        "protectedMaxAllowedetPdsgRmdrCs": 290,
        "MaxStopstPdsgRmdrCs": 440,
        "protectedMaxAllowedstPdsgRmdrCs": 290,
        "MaxStopwtPdsgRmdrCs": 440,
        "protectedMaxAllowedwtPdsgRmdrCs": 290
    },
    {
        "itstId": "21865",
        "itstNm": "동묘앞역(연등)1",
        "mapCtptIntLat": 37.5734609,
        "mapCtptIntLot": 127.0173311,
        "NewmapCtptIntLat": 37.5733711,
        "NewmapCtptIntLot": 127.0174444,
        "MaxStopsePdsgRmdrCs": 1340,
        "protectedMaxAllowedsePdsgRmdrCs": 360
    },
    {
        "itstId": "21923",
        "itstNm": "홍제역(연등)",
        "mapCtptIntLat": 37.5883918,
        "mapCtptIntLot": 126.9446584,
        "NewmapCtptIntLat": 37.588302,
        "NewmapCtptIntLot": 126.944545,
        "protectedMaxAllowedswPdsgRmdrCs": 380
    },
    {
        "itstId": "21999",
        "itstNm": "원남동사거리(연등)",
        "mapCtptIntLat": 37.57706,
        "mapCtptIntLot": 126.997248,
        "NewmapCtptIntLat": 37.57706,
        "NewmapCtptIntLot": 126.9973613,
        "MaxStopetPdsgRmdrCs": 1590,
        "protectedMaxAllowedetPdsgRmdrCs": 310
    },
    {
        "itstId": "22207",
        "itstNm": "국기원입구(연등)",
        "mapCtptIntLat": 37.4996489,
        "mapCtptIntLot": 127.0331074,
        "NewmapCtptIntLat": 37.4995591,
        "NewmapCtptIntLot": 127.0331074,
        "MaxStopstPdsgRmdrCs": 1230,
        "protectedMaxAllowedstPdsgRmdrCs": 360
    },
    {
        "itstId": "22212",
        "itstNm": "선릉역(연등)",
        "mapCtptIntLat": 37.5058405,
        "mapCtptIntLot": 127.0483914,
        "NewmapCtptIntLat": 37.5057507,
        "NewmapCtptIntLot": 127.0483914,
        "MaxStopstPdsgRmdrCs": 2550,
        "protectedMaxAllowedstPdsgRmdrCs": 300
    },
    {
        "itstId": "22262",
        "itstNm": "안국동사거리(연등)",
        "mapCtptIntLat": 37.5760636,
        "mapCtptIntLot": 126.9844131,
        "NewmapCtptIntLat": 37.5759738,
        "NewmapCtptIntLot": 126.9845264,
        "MaxStopsePdsgRmdrCs": 1220,
        "protectedMaxAllowedsePdsgRmdrCs": 380
    },
    {
        "itstId": "22287",
        "itstNm": "베네치아호텔(연등)",
        "mapCtptIntLat": 37.5048762,
        "mapCtptIntLot": 127.0350431,
        "NewmapCtptIntLat": 37.504966,
        "NewmapCtptIntLot": 127.0351563,
        "MaxStopnePdsgRmdrCs": 1250,
        "protectedMaxAllowednePdsgRmdrCs": 350
    },
    {
        "itstId": "22349",
        "itstNm": "떡전교사거리(연등)",
        "mapCtptIntLat": 37.5862687,
        "mapCtptIntLot": 127.0520015,
        "NewmapCtptIntLat": 37.5861789,
        "NewmapCtptIntLot": 127.0521149,
        "MaxStopsePdsgRmdrCs": 1380,
        "protectedMaxAllowedsePdsgRmdrCs": 310
    },
    {
        "itstId": "22379",
        "itstNm": "청량리역(연등)1",
        "mapCtptIntLat": 37.5806031,
        "mapCtptIntLot": 127.0458983,
        "NewmapCtptIntLat": 37.5805133,
        "NewmapCtptIntLot": 127.0460117,
        "MaxStopsePdsgRmdrCs": 1140,
        "protectedMaxAllowedsePdsgRmdrCs": 450
    },
    {
        "itstId": "22415",
        "itstNm": "가좌삼거리(연등)",
        "mapCtptIntLat": 37.569886,
        "mapCtptIntLot": 126.9135727,
        "NewmapCtptIntLat": 37.5697962,
        "NewmapCtptIntLot": 126.9134594,
        "MaxStopswPdsgRmdrCs": 950,
        "protectedMaxAllowedswPdsgRmdrCs": 450
    },
    {
        "itstId": "22419",
        "itstNm": "독립문삼호아파트(연등)",
        "mapCtptIntLat": 37.5716157,
        "mapCtptIntLot": 126.9590177,
        "NewmapCtptIntLat": 37.5717055,
        "NewmapCtptIntLot": 126.959131,
        "MaxStopnePdsgRmdrCs": 1380,
        "protectedMaxAllowednePdsgRmdrCs": 320
    },
    {
        "itstId": "22421",
        "itstNm": "동교동삼거리(연등)",
        "mapCtptIntLat": 37.5583715,
        "mapCtptIntLot": 126.9257768,
        "NewmapCtptIntLat": 37.5584613,
        "NewmapCtptIntLot": 126.9256635,
        "MaxStopnwPdsgRmdrCs": 1200,
        "protectedMaxAllowednwPdsgRmdrCs": 400
    },
    {
        "itstId": "22449",
        "itstNm": "신촌기차역(연등)1",
        "mapCtptIntLat": 37.5591279,
        "mapCtptIntLot": 126.9421012,
        "NewmapCtptIntLat": 37.5592177,
        "NewmapCtptIntLot": 126.9421012,
        "MaxStopntPdsgRmdrCs": 640,
        "protectedMaxAllowedntPdsgRmdrCs": 270
    },
    {
        "itstId": "22459",
        "itstNm": "연세대(연등)",
        "mapCtptIntLat": 37.5600824,
        "mapCtptIntLot": 126.9379651,
        "NewmapCtptIntLat": 37.5600824,
        "NewmapCtptIntLot": 126.9380784,
        "MaxStopetPdsgRmdrCs": 650,
        "protectedMaxAllowedetPdsgRmdrCs": 560
    },
    {
        "itstId": "22464",
        "itstNm": "연희IC(연등)",
        "mapCtptIntLat": 37.564288,
        "mapCtptIntLot": 126.9289894,
        "NewmapCtptIntLat": 37.5643778,
        "NewmapCtptIntLot": 126.9288761,
        "MaxStopnePdsgRmdrCs": 1020,
        "protectedMaxAllowednePdsgRmdrCs": 370,
        "MaxStopswPdsgRmdrCs": 740,
        "protectedMaxAllowedswPdsgRmdrCs": 650,
        "MaxStopnwPdsgRmdrCs": 1120,
        "protectedMaxAllowednwPdsgRmdrCs": 290
    },
    {
        "itstId": "22471",
        "itstNm": "인왕아파트(연등)",
        "mapCtptIntLat": 37.5850229,
        "mapCtptIntLot": 126.9482172,
        "NewmapCtptIntLat": 37.5851127,
        "NewmapCtptIntLot": 126.9481038,
        "MaxStopnePdsgRmdrCs": 1430,
        "protectedMaxAllowednePdsgRmdrCs": 350,
        "MaxStopsePdsgRmdrCs": 980,
        "protectedMaxAllowedsePdsgRmdrCs": 220,
        "MaxStopnwPdsgRmdrCs": 980,
        "protectedMaxAllowednwPdsgRmdrCs": 220
    },
    {
        "itstId": "22476",
        "itstNm": "충정로역(연등)",
        "mapCtptIntLat": 37.5593389,
        "mapCtptIntLot": 126.9635945,
        "NewmapCtptIntLat": 37.5594287,
        "NewmapCtptIntLot": 126.9635945,
        "MaxStopntPdsgRmdrCs": 1310,
        "protectedMaxAllowedntPdsgRmdrCs": 390
    },
    {
        "itstId": "22477",
        "itstNm": "국민연금북부(연등)",
        "mapCtptIntLat": 37.5621272,
        "mapCtptIntLot": 126.9640753,
        "NewmapCtptIntLat": 37.562217,
        "NewmapCtptIntLot": 126.9641886,
        "MaxStopnePdsgRmdrCs": 940,
        "protectedMaxAllowednePdsgRmdrCs": 240
    },
    {
        "itstId": "22481",
        "itstNm": "독립공원(연등)",
        "mapCtptIntLat": 37.5759207,
        "mapCtptIntLot": 126.9562014,
        "NewmapCtptIntLat": 37.5760105,
        "NewmapCtptIntLot": 126.9563147,
        "MaxStopnePdsgRmdrCs": 1400,
        "protectedMaxAllowednePdsgRmdrCs": 300
    },
    {
        "itstId": "22500",
        "itstNm": "굴다리입구(연등)",
        "mapCtptIntLat": 37.5598846,
        "mapCtptIntLot": 126.9403916,
        "NewmapCtptIntLat": 37.5598846,
        "NewmapCtptIntLot": 126.9402783,
        "MaxStopwtPdsgRmdrCs": 760,
        "protectedMaxAllowedwtPdsgRmdrCs": 230
    },
    {
        "itstId": "22580",
        "itstNm": "기독회관(연등)1",
        "mapCtptIntLat": 37.5746963,
        "mapCtptIntLot": 127.0021239,
        "NewmapCtptIntLat": 37.5746963,
        "NewmapCtptIntLot": 127.0022372,
        "protectedMaxAllowedetPdsgRmdrCs": 370
    },
    {
        "itstId": "22661",
        "itstNm": "ASEM입구(연등)",
        "mapCtptIntLat": 37.5104913,
        "mapCtptIntLot": 127.0579539,
        "NewmapCtptIntLat": 37.5104015,
        "NewmapCtptIntLot": 127.0578407,
        "MaxStopswPdsgRmdrCs": 2550,
        "protectedMaxAllowedswPdsgRmdrCs": 2550
    },
    {
        "itstId": "22705",
        "itstNm": "성신여대입구역(연등)1",
        "mapCtptIntLat": 37.5935387,
        "mapCtptIntLot": 127.0179452,
        "NewmapCtptIntLat": 37.5934489,
        "NewmapCtptIntLot": 127.0180586,
        "MaxStopsePdsgRmdrCs": 1170,
        "protectedMaxAllowedsePdsgRmdrCs": 410
    },
    {
        "itstId": "22823",
        "itstNm": "동대문역사문화공원(연등)",
        "mapCtptIntLat": 37.5662673,
        "mapCtptIntLot": 127.00678,
        "NewmapCtptIntLat": 37.5663571,
        "NewmapCtptIntLot": 127.0068933,
        "protectedMaxAllowednePdsgRmdrCs": 320
    },
    {
        "itstId": "22864",
        "itstNm": "을지로4가(연등)1",
        "mapCtptIntLat": 37.5673779,
        "mapCtptIntLot": 126.9980969,
        "NewmapCtptIntLat": 37.5673779,
        "NewmapCtptIntLot": 126.9982102,
        "MaxStopetPdsgRmdrCs": 970,
        "protectedMaxAllowedetPdsgRmdrCs": 420
    },
    {
        "itstId": "22866",
        "itstNm": "청계5가(연등)",
        "mapCtptIntLat": 37.5698376,
        "mapCtptIntLot": 127.0020403,
        "NewmapCtptIntLat": 37.5697478,
        "NewmapCtptIntLot": 127.0020403,
        "MaxStopntPdsgRmdrCs": 1180,
        "protectedMaxAllowedntPdsgRmdrCs": 650,
        "MaxStopstPdsgRmdrCs": 360,
        "protectedMaxAllowedstPdsgRmdrCs": 220
    },
    {
        "itstId": "22871",
        "itstNm": "충무로역(연등)",
        "mapCtptIntLat": 37.5611248,
        "mapCtptIntLot": 126.9926403,
        "NewmapCtptIntLat": 37.5612146,
        "NewmapCtptIntLot": 126.9926403,
        "MaxStopntPdsgRmdrCs": 1070,
        "protectedMaxAllowedntPdsgRmdrCs": 330
    },
    {
        "itstId": "22899",
        "itstNm": "숭례문정류장(연등)",
        "mapCtptIntLat": 37.5582468,
        "mapCtptIntLot": 126.9735227,
        "NewmapCtptIntLat": 37.5583366,
        "NewmapCtptIntLot": 126.9734094,
        "MaxStopnwPdsgRmdrCs": 650,
        "protectedMaxAllowednwPdsgRmdrCs": 400
    },
    {
        "itstId": "22902",
        "itstNm": "삼선빌딩(연등1)",
        "mapCtptIntLat": 37.5580674,
        "mapCtptIntLot": 126.9777238,
        "NewmapCtptIntLat": 37.5579776,
        "NewmapCtptIntLot": 126.9778371,
        "protectedMaxAllowedsePdsgRmdrCs": 290
    },
    {
        "itstId": "22905",
        "itstNm": "시청역2호선(연등)",
        "mapCtptIntLat": 37.5633687,
        "mapCtptIntLot": 126.9748938,
        "NewmapCtptIntLat": 37.5632789,
        "NewmapCtptIntLot": 126.9750071,
        "MaxStopsePdsgRmdrCs": 480,
        "protectedMaxAllowedsePdsgRmdrCs": 300
    },
    {
        "itstId": "22952",
        "itstNm": "청실종합(연등)1",
        "mapCtptIntLat": 37.4935611,
        "mapCtptIntLot": 127.0611541,
        "NewmapCtptIntLat": 37.4934713,
        "NewmapCtptIntLot": 127.0610409,
        "MaxStopswPdsgRmdrCs": 1230,
        "protectedMaxAllowedswPdsgRmdrCs": 370
    },
    {
        "itstId": "22953",
        "itstNm": "도곡역(연등)1",
        "mapCtptIntLat": 37.4898661,
        "mapCtptIntLot": 127.053075,
        "NewmapCtptIntLat": 37.4897763,
        "NewmapCtptIntLot": 127.0529618,
        "MaxStopswPdsgRmdrCs": 1240,
        "protectedMaxAllowedswPdsgRmdrCs": 350
    },
    {
        "itstId": "22958",
        "itstNm": "서초구민회관(연등)",
        "mapCtptIntLat": 37.4825733,
        "mapCtptIntLot": 127.036105,
        "NewmapCtptIntLat": 37.4824835,
        "NewmapCtptIntLot": 127.0359918,
        "MaxStopswPdsgRmdrCs": 1100,
        "protectedMaxAllowedswPdsgRmdrCs": 500
    },
    {
        "itstId": "22960",
        "itstNm": "영동1교(연등)",
        "mapCtptIntLat": 37.4717982,
        "mapCtptIntLot": 127.0386554,
        "NewmapCtptIntLat": 37.4717982,
        "NewmapCtptIntLot": 127.0385422,
        "MaxStopwtPdsgRmdrCs": 1130,
        "protectedMaxAllowedwtPdsgRmdrCs": 470
    },
    {
        "itstId": "22966",
        "itstNm": "휘문고교(연등)",
        "mapCtptIntLat": 37.5048324,
        "mapCtptIntLot": 127.0638745,
        "NewmapCtptIntLat": 37.5048324,
        "NewmapCtptIntLot": 127.0637613,
        "MaxStopwtPdsgRmdrCs": 1340,
        "protectedMaxAllowedwtPdsgRmdrCs": 260
    },
    {
        "itstId": "22969",
        "itstNm": "국민은행역삼(연등)",
        "mapCtptIntLat": 37.4955975,
        "mapCtptIntLot": 127.0287826,
        "NewmapCtptIntLat": 37.4955975,
        "NewmapCtptIntLot": 127.0286694,
        "MaxStopwtPdsgRmdrCs": 1060,
        "protectedMaxAllowedwtPdsgRmdrCs": 540
    },
    {
        "itstId": "22979",
        "itstNm": "씨티극장(연등)",
        "mapCtptIntLat": 37.501005,
        "mapCtptIntLot": 127.0261437,
        "NewmapCtptIntLat": 37.501005,
        "NewmapCtptIntLot": 127.0260305,
        "protectedMaxAllowedwtPdsgRmdrCs": 10
    },
    {
        "itstId": "22985",
        "itstNm": "영동시장(연등)",
        "mapCtptIntLat": 37.5064642,
        "mapCtptIntLot": 127.0235206,
        "NewmapCtptIntLat": 37.5064642,
        "NewmapCtptIntLot": 127.0234074,
        "MaxStopwtPdsgRmdrCs": 1110,
        "protectedMaxAllowedwtPdsgRmdrCs": 490
    },
    {
        "itstId": "22996",
        "itstNm": "역삼119안전센터(연등)",
        "mapCtptIntLat": 37.4978924,
        "mapCtptIntLot": 127.043397,
        "NewmapCtptIntLat": 37.4978026,
        "NewmapCtptIntLot": 127.0435102,
        "MaxStopsePdsgRmdrCs": 670,
        "protectedMaxAllowedsePdsgRmdrCs": 220
    },
    {
        "itstId": "23000",
        "itstNm": "영동2교북단(연등)",
        "mapCtptIntLat": 37.4809275,
        "mapCtptIntLot": 127.0420243,
        "NewmapCtptIntLat": 37.4810173,
        "NewmapCtptIntLot": 127.0419111,
        "MaxStopnwPdsgRmdrCs": 1290,
        "protectedMaxAllowednwPdsgRmdrCs": 310
    },
    {
        "itstId": "23007",
        "itstNm": "역삼초교(연등)",
        "mapCtptIntLat": 37.493584,
        "mapCtptIntLot": 127.0317641,
        "NewmapCtptIntLat": 37.4934942,
        "NewmapCtptIntLot": 127.0317641,
        "MaxStopstPdsgRmdrCs": 570,
        "protectedMaxAllowedstPdsgRmdrCs": 230
    },
    {
        "itstId": "23009",
        "itstNm": "도성초교사거리(연등)1",
        "mapCtptIntLat": 37.50154,
        "mapCtptIntLot": 127.0538682,
        "NewmapCtptIntLat": 37.50154,
        "NewmapCtptIntLot": 127.0539814,
        "MaxStopetPdsgRmdrCs": 1320,
        "protectedMaxAllowedetPdsgRmdrCs": 250
    },
    {
        "itstId": "23013",
        "itstNm": "싸리고개공원사거리(연등)1",
        "mapCtptIntLat": 37.4899793,
        "mapCtptIntLot": 127.0330263,
        "NewmapCtptIntLat": 37.4899793,
        "NewmapCtptIntLot": 127.0331395,
        "MaxStopetPdsgRmdrCs": 1320,
        "protectedMaxAllowedetPdsgRmdrCs": 270
    },
    {
        "itstId": "23014",
        "itstNm": "포이사거리(연등)",
        "mapCtptIntLat": 37.4770288,
        "mapCtptIntLot": 127.0452883,
        "NewmapCtptIntLat": 37.476939,
        "NewmapCtptIntLot": 127.0451751,
        "MaxStopswPdsgRmdrCs": 1290,
        "protectedMaxAllowedswPdsgRmdrCs": 310
    },
    {
        "itstId": "23019",
        "itstNm": "도곡1동주민센타(연등)",
        "mapCtptIntLat": 37.4928793,
        "mapCtptIntLot": 127.0424368,
        "NewmapCtptIntLat": 37.4927895,
        "NewmapCtptIntLot": 127.0424368,
        "MaxStopstPdsgRmdrCs": 1250,
        "protectedMaxAllowedstPdsgRmdrCs": 330
    },
    {
        "itstId": "23021",
        "itstNm": "한티역(연등)",
        "mapCtptIntLat": 37.4951276,
        "mapCtptIntLot": 127.0534337,
        "NewmapCtptIntLat": 37.4951276,
        "NewmapCtptIntLot": 127.0533205,
        "MaxStopwtPdsgRmdrCs": 1190,
        "protectedMaxAllowedwtPdsgRmdrCs": 390
    },
    {
        "itstId": "23023",
        "itstNm": "대치은마아파트(연등)",
        "mapCtptIntLat": 37.4959019,
        "mapCtptIntLot": 127.0625127,
        "NewmapCtptIntLat": 37.4959019,
        "NewmapCtptIntLot": 127.0623995,
        "MaxStopwtPdsgRmdrCs": 1200,
        "protectedMaxAllowedwtPdsgRmdrCs": 390
    },
    {
        "itstId": "23024",
        "itstNm": "우성2차201동앞(연등)",
        "mapCtptIntLat": 37.4994392,
        "mapCtptIntLot": 127.0625795,
        "NewmapCtptIntLat": 37.499529,
        "NewmapCtptIntLot": 127.0625795,
        "MaxStopntPdsgRmdrCs": 1170,
        "protectedMaxAllowedntPdsgRmdrCs": 410
    },
    {
        "itstId": "23027",
        "itstNm": "우리은행포이(연등)",
        "mapCtptIntLat": 37.4789812,
        "mapCtptIntLot": 127.0490829,
        "NewmapCtptIntLat": 37.479071,
        "NewmapCtptIntLot": 127.0490829,
        "MaxStopntPdsgRmdrCs": 2550,
        "protectedMaxAllowedntPdsgRmdrCs": 2550
    },
    {
        "itstId": "23028",
        "itstNm": "개포우성3차아파트(연등)1",
        "mapCtptIntLat": 37.4822523,
        "mapCtptIntLot": 127.0553883,
        "NewmapCtptIntLat": 37.4821625,
        "NewmapCtptIntLot": 127.0552751,
        "MaxStopswPdsgRmdrCs": 2550,
        "protectedMaxAllowedswPdsgRmdrCs": 2550
    },
    {
        "itstId": "23033",
        "itstNm": "개포2동주민센터(연등)",
        "mapCtptIntLat": 37.4893697,
        "mapCtptIntLot": 127.0677771,
        "NewmapCtptIntLat": 37.4892799,
        "NewmapCtptIntLot": 127.0677771,
        "MaxStopstPdsgRmdrCs": 730,
        "protectedMaxAllowedstPdsgRmdrCs": 260
    },
    {
        "itstId": "23045",
        "itstNm": "역삼영동아파트(연등)",
        "mapCtptIntLat": 37.4976195,
        "mapCtptIntLot": 127.052279,
        "NewmapCtptIntLat": 37.4976195,
        "NewmapCtptIntLot": 127.0521658,
        "MaxStopwtPdsgRmdrCs": 1290,
        "protectedMaxAllowedwtPdsgRmdrCs": 300
    },
    {
        "itstId": "23047",
        "itstNm": "휘문고정문(연등)",
        "mapCtptIntLat": 37.5038915,
        "mapCtptIntLot": 127.0611079,
        "NewmapCtptIntLat": 37.5039813,
        "NewmapCtptIntLot": 127.0609947,
        "MaxStopnwPdsgRmdrCs": 730,
        "protectedMaxAllowednwPdsgRmdrCs": 220
    },
    {
        "itstId": "23048",
        "itstNm": "대치사거리(연등)",
        "mapCtptIntLat": 37.5045022,
        "mapCtptIntLot": 127.0578997,
        "NewmapCtptIntLat": 37.504592,
        "NewmapCtptIntLot": 127.0580129,
        "MaxStopnePdsgRmdrCs": 1320,
        "protectedMaxAllowednePdsgRmdrCs": 270
    },
    {
        "itstId": "23049",
        "itstNm": "(구)역삼세무서(연등)1",
        "mapCtptIntLat": 37.4964708,
        "mapCtptIntLot": 127.0405227,
        "NewmapCtptIntLat": 37.4964708,
        "NewmapCtptIntLot": 127.0406359,
        "MaxStopetPdsgRmdrCs": 1380,
        "protectedMaxAllowedetPdsgRmdrCs": 210
    }
]